graphql_ws/__init__.py
graphql_ws/aiohttp.py
graphql_ws/base.py
graphql_ws/constants.py
graphql_ws/django_channels.py
graphql_ws/gevent.py
graphql_ws/observable_aiter.py
graphql_ws/websockets_lib.py
graphql_ws/pubsub/__init__.py
graphql_ws/pubsub/asyncio.py
graphql_ws/pubsub/gevent_observable.py
graphql_ws_subs-0.0.2.dist-info/AUTHORS.rst
graphql_ws_subs-0.0.2.dist-info/LICENSE
graphql_ws_subs-0.0.2.dist-info/METADATA
graphql_ws_subs-0.0.2.dist-info/WHEEL
graphql_ws_subs-0.0.2.dist-info/top_level.txt
graphql_ws_subs-0.0.2.dist-info/RECORD
