Metadata-Version: 2.1
Name: graphql-ws-subs
Version: 0.0.2
Summary: Websocket server for GraphQL subscriptions that includes subscriptions implementation from hballard
Home-page: https://github.com/cjayroe/graphql-ws
Author: Syrus Akbary
Author-email: me@syrusakbary.com
License: MIT
Keywords: graphql,subscriptions,graphene,websockets
Platform: UNKNOWN
Classifier: Development Status :: 2 - Pre-Alpha
Classifier: Intended Audience :: Developers
Classifier: License :: OSI Approved :: MIT License
Classifier: Natural Language :: English
Classifier: Programming Language :: Python :: 2
Classifier: Programming Language :: Python :: 2.6
Classifier: Programming Language :: Python :: 2.7
Classifier: Programming Language :: Python :: 3
Classifier: Programming Language :: Python :: 3.3
Classifier: Programming Language :: Python :: 3.4
Classifier: Programming Language :: Python :: 3.5
Classifier: Programming Language :: Python :: 3.6
Classifier: Programming Language :: Python :: 3.7
Classifier: Programming Language :: Python :: 3.8
Requires-Dist: graphql-core (==2.*)
Provides-Extra: dev
Requires-Dist: flake8 (<4,>=3.7) ; extra == 'dev'
Requires-Dist: tox (<4,>=3) ; extra == 'dev'
Requires-Dist: Sphinx (<2,>=1.8) ; extra == 'dev'
Provides-Extra: maintainer
Requires-Dist: bumpversion (>=0.5.3) ; extra == 'maintainer'
Requires-Dist: wheel (>=0.33.6) ; extra == 'maintainer'
Requires-Dist: PyYAML (<6,>=5.3) ; extra == 'maintainer'
Provides-Extra: test
Requires-Dist: pytest-cov ; extra == 'test'
Requires-Dist: graphene (<3,>=2.0) ; extra == 'test'
Requires-Dist: gevent ; extra == 'test'
Requires-Dist: graphene (>=2.0) ; extra == 'test'
Requires-Dist: graphene-django ; extra == 'test'
Requires-Dist: pytest (<5,>=4) ; (python_version < "3") and extra == 'test'
Requires-Dist: mock ; (python_version < "3") and extra == 'test'
Requires-Dist: django (==1.11.*) ; (python_version < "3") and extra == 'test'
Requires-Dist: channels (==1.*) ; (python_version < "3") and extra == 'test'
Requires-Dist: pytest (>5) ; (python_version >= "3") and extra == 'test'
Requires-Dist: django (==2.*) ; (python_version >= "3") and extra == 'test'
Requires-Dist: channels (==2.*) ; (python_version >= "3") and extra == 'test'
Requires-Dist: pytest-asyncio ; (python_version >= "3.4") and extra == 'test'
Requires-Dist: aiohttp ; (python_version >= "3.5") and extra == 'test'
